MemEval/__init__.py
memeval-0.0.1.dist-info/METADATA
memeval-0.0.1.dist-info/WHEEL
memeval-0.0.1.dist-info/top_level.txt
memeval-0.0.1.dist-info/RECORD
