Metadata-Version: 2.4
Name: memeval
Version: 0.0.1
Summary: Memory Evaluation.
Requires-Python: >=3.8
